[
  {
    "id": "k_10252806",
    "name": "대려도",
    "region": "서울 강남구 역삼로 118",
    "cat": "기타",
    "lat": 37.4935288570166,
    "lng": 127.032268469419,
    "place_url": "http://place.map.kakao.com/10252806",
    "icon": "🍽️",
    "tags": [
      "노포"
    ],
    "blog": 548
  },
  {
    "id": "k_11463001",
    "name": "알부자 강남본점",
    "region": "서울 강남구 강남대로98길 14",
    "cat": "횟집",
    "lat": 37.5007020002887,
    "lng": 127.027820307026,
    "place_url": "http://place.map.kakao.com/11463001",
    "icon": "🐟",
    "tags": [
      "핫플"
    ],
    "blog": 5974
  },
  {
    "id": "k_1238400864",
    "name": "땀땀 본점",
    "region": "서울 강남구 강남대로98길 12-5",
    "cat": "기타",
    "lat": 37.50040282892629,
    "lng": 127.0279785223454,
    "place_url": "http://place.map.kakao.com/1238400864",
    "icon": "🍽️",
    "tags": [
      "핫플",
      "혼밥",
      "맛집"
    ],
    "blog": 36693
  },
  {
    "id": "k_12418029",
    "name": "을밀대 강남점",
    "region": "서울 강남구 테헤란로4길 46",
    "cat": "면",
    "lat": 37.4952411777316,
    "lng": 127.030740331534,
    "place_url": "http://place.map.kakao.com/12418029",
    "icon": "🍜",
    "tags": [
      "노포",
      "핫플",
      "맛집"
    ],
    "blog": 32841
  },
  {
    "id": "k_13294737",
    "name": "해몽",
    "region": "서울 서초구 사평대로56길 8",
    "cat": "고기",
    "lat": 37.50323578049472,
    "lng": 127.02291746968591,
    "place_url": "http://place.map.kakao.com/13294737",
    "icon": "🍖",
    "tags": [
      "맛집"
    ],
    "blog": 10993
  },
  {
    "id": "k_13575898",
    "name": "갓덴스시 강남점",
    "region": "서울 강남구 테헤란로 109",
    "cat": "횟집",
    "lat": 37.498777145173,
    "lng": 127.029090699483,
    "place_url": "http://place.map.kakao.com/13575898",
    "icon": "🐟",
    "tags": [
      "핫플",
      "혼밥",
      "맛집"
    ],
    "blog": 29896
  },
  {
    "id": "k_1372079546",
    "name": "하이디라오 강남점",
    "region": "서울 서초구 서초대로77길 54",
    "cat": "기타",
    "lat": 37.502564150766105,
    "lng": 127.02480140187946,
    "place_url": "http://place.map.kakao.com/1372079546",
    "icon": "🍽️",
    "tags": [
      "핫플",
      "혼밥",
      "맛집"
    ],
    "blog": 116364
  },
  {
    "id": "k_1391619096",
    "name": "뱅뱅막국수",
    "region": "서울 강남구 도곡로 112",
    "cat": "한식",
    "lat": 37.48965346709964,
    "lng": 127.03283895681147,
    "place_url": "http://place.map.kakao.com/1391619096",
    "icon": "🍲",
    "tags": [
      "핫플",
      "혼밥"
    ],
    "blog": 5259
  },
  {
    "id": "k_1428481536",
    "name": "강남진해장",
    "region": "서울 강남구 테헤란로5길 11",
    "cat": "한식",
    "lat": 37.499584393000326,
    "lng": 127.02930814350843,
    "place_url": "http://place.map.kakao.com/1428481536",
    "icon": "🍲",
    "tags": [
      "혼밥",
      "맛집"
    ],
    "blog": 12648
  },
  {
    "id": "k_14569639",
    "name": "이도곰탕 본점",
    "region": "서울 강남구 논현로94길 29-5",
    "cat": "한식",
    "lat": 37.5033732001773,
    "lng": 127.038461247911,
    "place_url": "http://place.map.kakao.com/14569639",
    "icon": "🍲",
    "tags": [
      "혼밥"
    ],
    "blog": 6956
  },
  {
    "id": "k_1497416031",
    "name": "용가회전훠궈 강남점",
    "region": "서울 서초구 서초대로77길 43",
    "cat": "기타",
    "lat": 37.5013919194497,
    "lng": 127.024909582192,
    "place_url": "http://place.map.kakao.com/1497416031",
    "icon": "🍽️",
    "tags": [
      "핫플",
      "혼밥"
    ],
    "blog": 6636
  },
  {
    "id": "k_1511737742",
    "name": "돝고기506",
    "region": "서울 강남구 테헤란로 145",
    "cat": "고기",
    "lat": 37.50064504534292,
    "lng": 127.03528426481694,
    "place_url": "http://place.map.kakao.com/1511737742",
    "icon": "🍖",
    "tags": [
      "핫플"
    ],
    "blog": 1699
  },
  {
    "id": "k_16037196",
    "name": "논현손칼국수",
    "region": "서울 강남구 논현로111길 16",
    "cat": "면",
    "lat": 37.5076314148533,
    "lng": 127.032224774323,
    "place_url": "http://place.map.kakao.com/16037196",
    "icon": "🍜",
    "tags": [
      "혼밥"
    ],
    "blog": 5130
  },
  {
    "id": "k_16421356",
    "name": "농민백암순대 강남직영점",
    "region": "서울 강남구 역삼로3길 20-4",
    "cat": "한식",
    "lat": 37.49491300989233,
    "lng": 127.03150463098274,
    "place_url": "http://place.map.kakao.com/16421356",
    "icon": "🍲",
    "tags": [
      "핫플",
      "혼밥",
      "맛집"
    ],
    "blog": 14798
  },
  {
    "id": "k_1777540958",
    "name": "크래버대게나라 강남점",
    "region": "서울 강남구 언주로 620",
    "cat": "횟집",
    "lat": 37.5116883705501,
    "lng": 127.036257660784,
    "place_url": "http://place.map.kakao.com/1777540958",
    "icon": "🐟",
    "tags": [
      "맛집"
    ],
    "blog": 20467
  },
  {
    "id": "k_22211960",
    "name": "로리스더프라임립",
    "region": "서울 서초구 서초대로 411",
    "cat": "기타",
    "lat": 37.49808140984054,
    "lng": 127.02590025308936,
    "place_url": "http://place.map.kakao.com/22211960",
    "icon": "🍽️",
    "tags": [
      "노포",
      "핫플",
      "혼밥"
    ],
    "blog": 9656
  },
  {
    "id": "k_25038356",
    "name": "임병주 산동칼국수",
    "region": "서울 서초구 강남대로37길 65",
    "cat": "면",
    "lat": 37.48456982587015,
    "lng": 127.03003042469688,
    "place_url": "http://place.map.kakao.com/25038356",
    "icon": "🍜",
    "tags": [
      "혼밥"
    ],
    "blog": 5829
  },
  {
    "id": "k_27315574",
    "name": "삼육가 논현직영점",
    "region": "서울 강남구 강남대로114길 8",
    "cat": "고기",
    "lat": 37.50567257412158,
    "lng": 127.02501731668784,
    "place_url": "http://place.map.kakao.com/27315574",
    "icon": "🍖",
    "tags": [
      "맛집"
    ],
    "blog": 15800
  },
  {
    "id": "k_27455203",
    "name": "왓쇼이켄",
    "region": "서울 강남구 테헤란로4길 46",
    "cat": "횟집",
    "lat": 37.495129567990034,
    "lng": 127.0302947416335,
    "place_url": "http://place.map.kakao.com/27455203",
    "icon": "🐟",
    "tags": [
      "핫플",
      "혼밥"
    ],
    "blog": 1064
  },
  {
    "id": "k_34321780",
    "name": "서관면옥 교대본점",
    "region": "서울 서초구 서초대로56길 11",
    "cat": "면",
    "lat": 37.49397890313892,
    "lng": 127.01725609065346,
    "place_url": "http://place.map.kakao.com/34321780",
    "icon": "🍜",
    "tags": [
      "혼밥",
      "맛집"
    ],
    "blog": 9813
  },
  {
    "id": "k_539250139",
    "name": "크라이치즈버거 양재역점",
    "region": "서울 서초구 강남대로41길 8",
    "cat": "기타",
    "lat": 37.4872543308294,
    "lng": 127.031935604809,
    "place_url": "http://place.map.kakao.com/539250139",
    "icon": "🍽️",
    "tags": [
      "혼밥"
    ],
    "blog": 8071
  },
  {
    "id": "k_741391811",
    "name": "육전식당 4호점",
    "region": "서울 강남구 테헤란로22길 12",
    "cat": "고기",
    "lat": 37.49906479206695,
    "lng": 127.03490919928926,
    "place_url": "http://place.map.kakao.com/741391811",
    "icon": "🍖",
    "tags": [
      "맛집"
    ],
    "blog": 221620
  },
  {
    "id": "k_770095922",
    "name": "청류벽",
    "region": "서울 서초구 서초대로74길 29",
    "cat": "면",
    "lat": 37.49490503104327,
    "lng": 127.02736582882774,
    "place_url": "http://place.map.kakao.com/770095922",
    "icon": "🍜",
    "tags": [
      "노포",
      "핫플"
    ],
    "blog": 2288
  },
  {
    "id": "k_7819490",
    "name": "대우부대찌개",
    "region": "서울 강남구 테헤란로25길 34",
    "cat": "한식",
    "lat": 37.502696655575825,
    "lng": 127.03521737405278,
    "place_url": "http://place.map.kakao.com/7819490",
    "icon": "🍲",
    "tags": [
      "노포"
    ],
    "blog": 4474
  },
  {
    "id": "k_7983060",
    "name": "신동궁감자탕뼈숯불구이 역삼직영점",
    "region": "서울 강남구 테헤란로10길 21",
    "cat": "한식",
    "lat": 37.49788594917416,
    "lng": 127.03290815160956,
    "place_url": "http://place.map.kakao.com/7983060",
    "icon": "🍲",
    "tags": [
      "노포",
      "핫플",
      "혼밥",
      "맛집"
    ],
    "blog": 21922
  },
  {
    "id": "k_8144397",
    "name": "강강술래 역삼점",
    "region": "서울 강남구 논현로 325",
    "cat": "한식",
    "lat": 37.49418343234461,
    "lng": 127.03968572363503,
    "place_url": "http://place.map.kakao.com/8144397",
    "icon": "🍲",
    "tags": [
      "맛집"
    ],
    "blog": 15388
  },
  {
    "id": "k_8323721",
    "name": "버드나무집 서초본점",
    "region": "서울 서초구 효령로 434",
    "cat": "고기",
    "lat": 37.48913764364786,
    "lng": 127.0311629855974,
    "place_url": "http://place.map.kakao.com/8323721",
    "icon": "🍖",
    "tags": [
      "맛집"
    ],
    "blog": 10811
  },
  {
    "id": "k_850873071",
    "name": "정돈 강남점",
    "region": "서울 강남구 강남대로110길 19-1",
    "cat": "횟집",
    "lat": 37.503909008238786,
    "lng": 127.02638857680932,
    "place_url": "http://place.map.kakao.com/850873071",
    "icon": "🐟",
    "tags": [
      "혼밥"
    ],
    "blog": 1840393
  },
  {
    "id": "k_23578013",
    "name": "뚜쥬루 돌가마점",
    "region": "충남 천안시 동남구 풍세로 706",
    "cat": "카페",
    "lat": 36.77312336918423,
    "lng": 127.13965203895398,
    "icon": "☕",
    "place_url": "http://place.map.kakao.com/23578013",
    "tags": [
      "맛집"
    ],
    "blog": 9187
  },
  {
    "id": "k_27303343",
    "name": "밥상차려주는집 천안본점",
    "region": "충남 천안시 동남구 풍세로 702",
    "cat": "한식",
    "lat": 36.77294752995506,
    "lng": 127.13898636550012,
    "icon": "🍲",
    "place_url": "http://place.map.kakao.com/27303343",
    "tags": [
      "노포",
      "핫플",
      "혼밥"
    ],
    "blog": 617692
  },
  {
    "id": "k_15527020",
    "name": "정가네포차",
    "region": "충남 천안시 동남구 풍세로 769-21",
    "cat": "기타",
    "lat": 36.7795165536755,
    "lng": 127.138307048915,
    "icon": "🍽️",
    "place_url": "http://place.map.kakao.com/15527020",
    "tags": [
      "노포",
      "혼밥"
    ],
    "blog": 1300
  },
  {
    "id": "k_1206739994",
    "name": "자반고 천안동남점",
    "region": "충남 천안시 동남구 풍세로 712",
    "cat": "횟집",
    "lat": 36.77293527206955,
    "lng": 127.14021736105059,
    "icon": "🐟",
    "place_url": "http://place.map.kakao.com/1206739994",
    "tags": [
      "핫플"
    ],
    "blog": 4009
  },
  {
    "id": "k_25811180",
    "name": "천상대게",
    "region": "충남 천안시 동남구 풍세로 698",
    "cat": "횟집",
    "lat": 36.772426655240395,
    "lng": 127.1382383066383,
    "icon": "🐟",
    "place_url": "http://place.map.kakao.com/25811180",
    "tags": [
      "맛집"
    ],
    "blog": 5797
  },
  {
    "id": "k_1834994382",
    "name": "천안축산농협 한우프라자 청당점",
    "region": "충남 천안시 동남구 광풍로 1775",
    "cat": "고기",
    "lat": 36.7773483349614,
    "lng": 127.142994506925,
    "icon": "🍖",
    "place_url": "http://place.map.kakao.com/1834994382",
    "tags": [
      "노포",
      "혼밥"
    ],
    "blog": 3081
  },
  {
    "id": "k_1988492767",
    "name": "왕새우나라 용곡신방점",
    "region": "충남 천안시 동남구 풍세로 769-33",
    "cat": "횟집",
    "lat": 36.7799809945712,
    "lng": 127.13721230059,
    "icon": "🐟",
    "place_url": "http://place.map.kakao.com/1988492767",
    "tags": [
      "맛집"
    ],
    "blog": 15130
  },
  {
    "id": "k_1070508065",
    "name": "몰랑몰랑",
    "region": "충남 천안시 동남구 통정10로 43-27",
    "cat": "카페",
    "lat": 36.77341915823651,
    "lng": 127.13317036949465,
    "icon": "☕",
    "place_url": "http://place.map.kakao.com/1070508065",
    "tags": [
      "맛집"
    ],
    "blog": 12571
  },
  {
    "id": "k_1427825107",
    "name": "구룡정육도",
    "region": "충남 천안시 동남구 광풍로 1698",
    "cat": "고기",
    "lat": 36.77023503553661,
    "lng": 127.14365110786784,
    "icon": "🍖",
    "place_url": "http://place.map.kakao.com/1427825107",
    "tags": [
      "노포",
      "혼밥"
    ],
    "blog": 215
  },
  {
    "id": "k_1567454041",
    "name": "명품손칼국수",
    "region": "충남 천안시 동남구 통정5로 8",
    "cat": "면",
    "lat": 36.77092437176992,
    "lng": 127.12953918347283,
    "icon": "🍜",
    "place_url": "http://place.map.kakao.com/1567454041",
    "tags": [
      "노포",
      "맛집"
    ],
    "blog": 14400
  },
  {
    "id": "k_252582798",
    "name": "아구드림 신방통정점",
    "region": "충남 천안시 동남구 통정1로 27-30",
    "cat": "횟집",
    "lat": 36.7780530509213,
    "lng": 127.129584784144,
    "icon": "🐟",
    "place_url": "http://place.map.kakao.com/252582798",
    "tags": [
      "혼밥",
      "맛집"
    ],
    "blog": 8172
  },
  {
    "id": "k_866479873",
    "name": "동경닭발 본점",
    "region": "충남 천안시 동남구 통정10로 68",
    "cat": "고기",
    "lat": 36.7734441426879,
    "lng": 127.134191973784,
    "icon": "🍖",
    "place_url": "http://place.map.kakao.com/866479873",
    "tags": [
      "노포",
      "혼밥"
    ],
    "blog": 2126
  },
  {
    "id": "k_1621412533",
    "name": "전설렁탕",
    "region": "충남 천안시 동남구 통정5로 89",
    "cat": "한식",
    "lat": 36.7764623899967,
    "lng": 127.135420467538,
    "icon": "🍲",
    "place_url": "http://place.map.kakao.com/1621412533",
    "tags": [
      "혼밥",
      "맛집"
    ],
    "blog": 202453
  },
  {
    "id": "k_1842989282",
    "name": "늘봄식당",
    "region": "충남 천안시 동남구 신방통정로 84",
    "cat": "횟집",
    "lat": 36.76835712394155,
    "lng": 127.13115334984265,
    "icon": "🐟",
    "place_url": "http://place.map.kakao.com/1842989282",
    "tags": [
      "맛집"
    ],
    "blog": 13909
  },
  {
    "id": "k_24897921",
    "name": "짬뽕사랑",
    "region": "충남 천안시 동남구 통정12로 6",
    "cat": "기타",
    "lat": 36.7784854195192,
    "lng": 127.128908907445,
    "icon": "🍽️",
    "place_url": "http://place.map.kakao.com/24897921",
    "tags": [
      "혼밥",
      "맛집"
    ],
    "blog": 414219
  },
  {
    "id": "k_23790840",
    "name": "춘천호반숯불닭갈비",
    "region": "충남 천안시 동남구 통정12로 76-4",
    "cat": "고기",
    "lat": 36.77569398954258,
    "lng": 127.13519956349015,
    "icon": "🍖",
    "place_url": "http://place.map.kakao.com/23790840",
    "tags": [
      "맛집"
    ],
    "blog": 137314
  },
  {
    "id": "k_356250088",
    "name": "삼동소바 천안구룡점",
    "region": "충남 천안시 동남구 광풍로 1707",
    "cat": "횟집",
    "lat": 36.7709103612775,
    "lng": 127.142578195878,
    "icon": "🐟",
    "place_url": "http://place.map.kakao.com/356250088",
    "tags": [
      "핫플",
      "혼밥",
      "맛집"
    ],
    "blog": 24180
  },
  {
    "id": "k_19736218",
    "name": "우밀칼국수",
    "region": "충남 천안시 동남구 통정4로 45",
    "cat": "면",
    "lat": 36.7751306591225,
    "lng": 127.134521999235,
    "icon": "🍜",
    "place_url": "http://place.map.kakao.com/19736218",
    "tags": [
      "혼밥"
    ],
    "blog": 262
  }
]
